Amisynth/__init__.py
Amisynth/client.py
Amisynth/utils.py
Amisynth/Collector/__init__.py
Amisynth/Functions/__init__.py
Amisynth/Functions/setPrefix.py
Amisynth/Functions/storage.py
Amisynth/Functions/Admin/__init__.py
Amisynth/Functions/Admin/ban.py
Amisynth/Functions/Admin/kick.py
Amisynth/Functions/Admin/unban.py
Amisynth/Functions/Bot/__init__.py
Amisynth/Functions/Bot/ping.py
Amisynth/Functions/Buttons/__init__.py
Amisynth/Functions/Buttons/addButton.py
Amisynth/Functions/Buttons/customID.py
Amisynth/Functions/Buttons/editButton.py
Amisynth/Functions/Buttons/removeButtons.py
Amisynth/Functions/Buttons/removeComponent.py
Amisynth/Functions/Canvas/__init__.py
Amisynth/Functions/Canvas/addCircleCanvas.py
Amisynth/Functions/Canvas/addElipseCanvas.py
Amisynth/Functions/Canvas/addPolygonCanvas.py
Amisynth/Functions/Canvas/addRectangle.py
Amisynth/Functions/Canvas/addTextCanvas.py
Amisynth/Functions/Canvas/createCanvas.py
Amisynth/Functions/Canvas/getCanvas.py
Amisynth/Functions/Canvas/loadCanvas.py
Amisynth/Functions/Canvas/pasteCanvas.py
Amisynth/Functions/Canvas/saveCanvas.py
Amisynth/Functions/Channels/__init__.py
Amisynth/Functions/Channels/categoryIDs.py
Amisynth/Functions/Channels/categoryNames.py
Amisynth/Functions/Channels/channelID.py
Amisynth/Functions/Channels/channelName.py
Amisynth/Functions/Channels/channelNames.py
Amisynth/Functions/Channels/channelPosition.py
Amisynth/Functions/Channels/channelSystem.py
Amisynth/Functions/Channels/channelsIDs.py
Amisynth/Functions/Channels/createChannel.py
Amisynth/Functions/Channels/editChannelAfter.py
Amisynth/Functions/Channels/editChannelBefore.py
Amisynth/Functions/Channels/findChannel.py
Amisynth/Functions/Channels/mentionedChannels.py
Amisynth/Functions/Conditions/__init__.py
Amisynth/Functions/Conditions/and.py
Amisynth/Functions/Conditions/argsCheck.py
Amisynth/Functions/Conditions/checkCondition.py
Amisynth/Functions/Conditions/checkContains.py
Amisynth/Functions/Conditions/or.py
amisynth-0.3.14.dist-info/METADATA
amisynth-0.3.14.dist-info/WHEEL
amisynth-0.3.14.dist-info/top_level.txt
amisynth-0.3.14.dist-info/RECORD
