Metadata-Version: 2.4
Name: Amisynth
Version: 0.3.14
Summary: Crea tu bot de discord sin saber programar!
Home-page: https://github.com/Amisynth/Amisynth
Author: Amisinth
Author-email: amisynth@gmail.com
Classifier: Programming Language :: Python :: 3
Classifier: License :: OSI Approved :: MIT License
Classifier: Operating System :: OS Independent
Requires-Python: >=3.6
Requires-Dist: discord.py
Requires-Dist: asyncio
Requires-Dist: xfox
Requires-Dist: youtube_search
Requires-Dist: aiohttp
Dynamic: author
Dynamic: author-email
Dynamic: classifier
Dynamic: description
Dynamic: description-content-type
Dynamic: home-page
Dynamic: requires-dist
Dynamic: requires-python
Dynamic: summary
